{
    "Changes": [
      {
        "LogName": "PoisonTile",
        "Action": "EditMap",
        "Target": "Maps/Farm",
        "MapTiles": [
          {
            "Position": {
              "X": {
                "Min": 64,
                "Max": 70
              },
              "Y": {
                "Min": 18,
                "Max": 20
              }
            },
            "Layer": "Paths",
            "Properties": {
              "TouchAction": "Poison"
            },
            "Index": 622
          }
        ]
      },
      {
        "Action": "EditData",
        "Target": "Data/Buffs",
        "Entries": {
          "Poison": {
            "Description": "You are poisoned!",
            "TimeToFadeOut": 50,
            "BuffAttributes": "0 0 0 0 0 0 0 -1 0 0 0 0 0 0 0 0 0 0",
            "IsNegative": true,
            "BuffIcon": "LooseSprites\\Cursors",
            "SourceRect": {
              "X": 355,
              "Y": 412,
              "Width": 16,
              "Height": 16
            }
          }
        }
      }
    ]
  }